MANIFEST.in
readme.md
setup.py
doc/chaining-dh.txt
doc/fileformats.txt
pbp/__init__.py
pbp/axolotl.py
pbp/chaining.py
pbp/ecdh.py
pbp/main.py
pbp/merkle.py
pbp/pbp.py
pbp/pitchfork.py
pbp/publickey.py
pbp/seeder.py
pbp/seedstore.py
pbp/simplesign.py
pbp/utils.py
pbp.egg-info/PKG-INFO
pbp.egg-info/SOURCES.txt
pbp.egg-info/dependency_links.txt
pbp.egg-info/entry_points.txt
pbp.egg-info/requires.txt
pbp.egg-info/top_level.txt