Metadata-Version: 1.1
Name: pbp
Version: 0.3.2
Summary: simple crypto tool
Home-page: https://github.com/stef/pbp
Author: Stefan Marsiske
Author-email: s@ctrlc.hu
License: AGPLv3
Keywords: cryptography API NaCl libsodium
Platform: UNKNOWN
Classifier: Development Status :: 4 - Beta
Classifier: License :: OSI Approved :: GNU Affero General Public License v3 or later (AGPLv3+)
Classifier: Topic :: Security :: Cryptography
Classifier: Topic :: Security
